{
    "version": 0.8,
    "RegionId": 12854,
    "CitizenList": [
        {
            "name": "Lily",
            "examineText": "Farming... such a peaceful life.",
            "remarks": [
                "I thought I saw a Tangleroot..."
            ],
            "modelRecolorFind": [
                4550,
                25238,
                6798,
                9096,
                54397,
                8741
            ],
            "modelRecolorReplace": [
                4562,
                5400,
                7465,
                5400,
                8497,
                12700
            ],
            "worldPoint": {
                "x": 3227,
                "y": 3459,
                "plane": 0
            },
            "modelIds": [
                217,
                8798,
                390,
                7366,
                471,
                4392,
                348,
                353,
                46747,
                437
            ],
            "idleAnimation": "FireCook",
            "moveAnimation": "HumanWalk",
            "baseOrientation": 1536
        }
    ]
}